newyorker/__init__.py
newyorker/cartoons.py
tests/__init__.py
tests/test_basic.py
tests/data/test_data.yaml
newyorker-1.1.0.dist-info/LICENSE
newyorker-1.1.0.dist-info/METADATA
newyorker-1.1.0.dist-info/WHEEL
newyorker-1.1.0.dist-info/entry_points.txt
newyorker-1.1.0.dist-info/top_level.txt
newyorker-1.1.0.dist-info/RECORD
