Metadata-Version: 2.1
Name: newyorker
Version: 1.1.0
Summary: Search by keywords and download cartoons from The New Yorker magazine cartoon gallery
Home-page: https://github.com/Demonofthe2ndkind/new-yorker.git
Author: Demon of the Second Kind
Author-email: demonofthe2ndkind@sevanya.com
License: Apache Software License
Platform: UNKNOWN
Classifier: Programming Language :: Python :: 3
Classifier: License :: OSI Approved :: Apache Software License
Classifier: Operating System :: OS Independent
Requires-Python: >=3.8
Requires-Dist: beautifulsoup4 (>=4.9.1)
Requires-Dist: requests (>=2.24.0)
